grounding_server/grounding_server.py
mitm_addons/mitm_grounding_addon.py
mitm_addons/mitm_split_addon.py
yandex_captcha_puzzle_solver/__init__.py
yandex_captcha_puzzle_solver/browser_wrapper.py
yandex_captcha_puzzle_solver/image_processor.py
yandex_captcha_puzzle_solver/proxy_controller.py
yandex_captcha_puzzle_solver/yandex_captcha_puzzle_solve_server.py
yandex_captcha_puzzle_solver/yandex_captcha_puzzle_solver.py
yandex_captcha_puzzle_solver-0.1.2.dist-info/LICENSE
yandex_captcha_puzzle_solver-0.1.2.dist-info/METADATA
yandex_captcha_puzzle_solver-0.1.2.dist-info/WHEEL
yandex_captcha_puzzle_solver-0.1.2.dist-info/entry_points.txt
yandex_captcha_puzzle_solver-0.1.2.dist-info/top_level.txt
yandex_captcha_puzzle_solver-0.1.2.dist-info/RECORD
