Metadata-Version: 2.1
Name: yandex_captcha_puzzle_solver
Version: 0.1.2
Author-email: yoori <yuri.kuznecov@gmail.com>
License: GNU Lesser General Public License
Project-URL: homepage, https://github.com/yoori/flare-bypasser
Requires-Python: >=3.9
License-File: LICENSE
Requires-Dist: asyncio
Requires-Dist: uuid
Requires-Dist: urllib3
Requires-Dist: websockets==14.0
Requires-Dist: zendriver_flare_bypasser==0.2.4
Requires-Dist: argparse
Requires-Dist: oslex
Requires-Dist: jinja2
Requires-Dist: fastapi
Requires-Dist: uvicorn
Requires-Dist: xvfbwrapper==0.2.9; platform_system != "Windows"
Requires-Dist: gunicorn; platform_system != "Windows"
Requires-Dist: numpy
Requires-Dist: opencv-python
